telebox/__init__.py
telebox/errors.py
telebox/bot/__init__.py
telebox/bot/bot.py
telebox/bot/context.py
telebox/bot/errors.py
telebox/bot/consts/__init__.py
telebox/bot/consts/admin_rights.py
telebox/bot/consts/background_fill_types.py
telebox/bot/consts/background_types.py
telebox/bot/consts/bot_command_scope_types.py
telebox/bot/consts/chat_actions.py
telebox/bot/consts/chat_member_statuses.py
telebox/bot/consts/chat_types.py
telebox/bot/consts/country_codes.py
telebox/bot/consts/currencies.py
telebox/bot/consts/dice_emojis.py
telebox/bot/consts/encrypted_passport_element_types.py
telebox/bot/consts/inline_query_chat_types.py
telebox/bot/consts/inline_query_result_types.py
telebox/bot/consts/input_media_types.py
telebox/bot/consts/input_paid_media_types.py
telebox/bot/consts/language_codes.py
telebox/bot/consts/mask_position_points.py
telebox/bot/consts/menu_button_types.py
telebox/bot/consts/message_entity_types.py
telebox/bot/consts/paid_media_types.py
telebox/bot/consts/parse_modes.py
telebox/bot/consts/passport_element_error_sources.py
telebox/bot/consts/poll_types.py
telebox/bot/consts/reaction_types.py
telebox/bot/consts/sticker_types.py
telebox/bot/consts/transaction_partner_types.py
telebox/bot/consts/update_types.py
telebox/bot/consts/withdrawal_state_types.py
telebox/bot/enums/__init__.py
telebox/bot/enums/input_file_type.py
telebox/bot/enums/message_content_type.py
telebox/bot/enums/update_content_type.py
telebox/bot/types/__init__.py
telebox/bot/types/type.py
telebox/bot/types/types/__init__.py
telebox/bot/types/types/animation.py
telebox/bot/types/types/audio.py
telebox/bot/types/types/background_fill.py
telebox/bot/types/types/background_fill_freeform_gradient.py
telebox/bot/types/types/background_fill_gradient.py
telebox/bot/types/types/background_fill_solid.py
telebox/bot/types/types/background_type.py
telebox/bot/types/types/background_type_chat_theme.py
telebox/bot/types/types/background_type_fill.py
telebox-0.34.0.dist-info/METADATA
telebox-0.34.0.dist-info/WHEEL
telebox-0.34.0.dist-info/entry_points.txt
telebox-0.34.0.dist-info/licenses/LICENSE
telebox-0.34.0.dist-info/RECORD
