Metadata-Version: 2.3
Name: telebox
Version: 0.34.0
Summary: A Python framework for creating Telegram bots.
Project-URL: Homepage, https://github.com/Abstract-X/telebox
Project-URL: Bug Tracker, https://github.com/Abstract-X/telebox/issues
Author-email: Abstract-X <abstract-x-mail@protonmail.com>
License: MIT License
Classifier: License :: OSI Approved :: MIT License
Classifier: Operating System :: OS Independent
Classifier: Programming Language :: Python :: 3
Requires-Python: >=3.9
Requires-Dist: dataclass-factory<3,>=2.16
Requires-Dist: orjson<4,>=3.9.10
Requires-Dist: requests-toolbelt>=0.10.1
Requires-Dist: requests<3,>=2.28.2
Requires-Dist: xcept<4,>=3.1.0
Provides-Extra: codegen
Requires-Dist: jinja2<4,>=3.1.2; extra == 'codegen'
Provides-Extra: server
Requires-Dist: cherrypy<19,>=18.8.0; extra == 'server'
